{
  "duration": {
    "human": "1:23",
    "inSeconds": 83
  },
  "episode": {
    "index": 37,
    "name": "J'y pense et je souris.",
    "slug": "brefJyPenseEtJeSouris"
  },
  "lines": [
    {
      "content": "Bref, en 1873, pendant la période Bouc\net Moustache, Amé Débolé commercialise\nen France la première automobile.",
      "end": 5,
      "start": 0
    },
    {
      "content": "Elle s'appelle l'Obéissante,\ndéjà un fantasme masculin.",
      "end": 7,
      "start": 5
    },
    {
      "content": "Pendant ce temps, en Pennsylvania,\nEdwin Drake, d'armée moustache,\nfort imput de pétrole et provoque\nla naissance de l'industrie pétrolière.",
      "end": 12,
      "start": 7
    },
    {
      "content": "Il devient très riche.",
      "end": 13,
      "start": 12
    },
    {
      "content": "À peu près à la même époque,\nà Mussy, la ville, en Belgique,\nJean-Joseph Étienne Le Noir,\nqui porte très bien la moustache, invente",
      "end": 17,
      "start": 13
    },
    {
      "content": "le premier moteur à combustion interne.",
      "end": 19,
      "start": 17
    },
    {
      "content": "C'est ce moteur qui conviendra\nle mieux à la voiture.",
      "end": 21,
      "start": 19
    },
    {
      "content": "L'humidité est un vrai feuillot pour ma\nsalle de bains, mais depuis toujours,\ncelle qui s'évapore depuis\nles grandes étendues d'eau se refroidit",
      "end": 25,
      "start": 21
    },
    {
      "content": "et se condense dans le ciel en nuage.",
      "end": 26,
      "start": 25
    },
    {
      "content": "Des gouttes se forment,\nelles tombent, il pleut.",
      "end": 28,
      "start": 26
    },
    {
      "content": "Entre deux taillettes de bouc\net moustache, Amé déboîlé réfléchi aux\nmeilleurs moyens de vendre l'obéissante.",
      "end": 31,
      "start": 28
    },
    {
      "content": "Pendant ce temps, Thomas\nEdison, propre sur lui et bien rasé,\ninvente la lampe électrique.",
      "end": 35,
      "start": 31
    },
    {
      "content": "En 1908, le fortisme créé par Henry Ford,\ntout le temps bien rasé aussi, popularise\nl'automobile et le rend très riche aussi.",
      "end": 39,
      "start": 35
    },
    {
      "content": "De plus en plus de gens\nont accès à la voiture.",
      "end": 41,
      "start": 39
    },
    {
      "content": "Dans les années 80, mon père,\ndans sa période moustache, convaincu par\nles publicités dans leur période cocaïne\nà gogo, achète une voiture pour aller",
      "end": 46,
      "start": 41
    },
    {
      "content": "à la campagne avec mon frère et moi.",
      "end": 48,
      "start": 47
    },
    {
      "content": "La rotation de la terre sur son axe\nfait alterner la nuit et le jour.",
      "end": 50,
      "start": 48
    },
    {
      "content": "En hiver, les nuits sont plus longues.",
      "end": 51,
      "start": 50
    },
    {
      "content": "Tôt le soir, il fait déjà nuit noire.\nIl y a des voitures partout.",
      "end": 53,
      "start": 51
    },
    {
      "content": "Il faut aménager les routes.",
      "end": 54,
      "start": 53
    },
    {
      "content": "Les garnirs de platanes,\nles équipés de lampadaires éclairant\nla chaussée grâce à des ampoules.\nDehors, il y a plein de lumière.",
      "end": 58,
      "start": 54
    },
    {
      "content": "À 12 ans, trois mois et six jours,\nj'étais dans une voiture imaginée\npar Amé Débollet, roulant grâce au moteur\nimaginé par Jean-Joseph Étienne Lenoir,",
      "end": 64,
      "start": 58
    },
    {
      "content": "alimenté par de l'essence,\net trouvé par Edwin Drake,\nachetée par mon père grâce à Henry Ford,\nla publicité et les cocaïnomans,",
      "end": 69,
      "start": 64
    },
    {
      "content": "sur une route de nuit éclairée par les\nampoules inventées par Thomas Edison.",
      "end": 71,
      "start": 69
    },
    {
      "content": "Il pleuvait.\nJ'ai posé ma tête contre la vitre.",
      "end": 74,
      "start": 71
    },
    {
      "content": "C'était l'une des plus belles choses\nque j'ai vues dans ma vie.",
      "end": 76,
      "start": 74
    },
    {
      "content": "Bref, des fois, j'y pense et je souris.",
      "end": 80,
      "start": 76
    }
  ],
  "video": {
    "id": "O1BZzYB3X6U",
    "viewcount": 5100000
  }
}
